README.rst
setup.py
tests/__init__.py
voldemort/__init__.py
voldemort/config.py
voldemort/filters.py
voldemort/paginator.py
voldemort/template.py
voldemort/util.py
voldemort.egg-info/PKG-INFO
voldemort.egg-info/SOURCES.txt
voldemort.egg-info/dependency_links.txt
voldemort.egg-info/entry_points.txt
voldemort.egg-info/requires.txt
voldemort.egg-info/top_level.txt
voldemort.egg-info/zip-safe