Metadata-Version: 1.1
Name: voldemort
Version: 0.8.0
Summary: Voldemort is a simple static site generator                     using Jinja2 and Markdown templates.
Home-page: https://github.com/semk/voldemort
Author: Sreejith K / K7Computing Pvt Ltd
Author-email: sreejithemk@gmail.com
License: Apache License, Version 2.0
Download-URL: https://github.com/semk/voldemort/tarball/master#egg=voldemort-0.8.0
Keywords: Voldemort Static Site Generator Jinja Jinja2                     Markdown Blog Python
Platform: any
Classifier: Operating System :: POSIX
Classifier: Programming Language :: Python
Classifier: Environment :: Web Environment
Classifier: Topic :: Internet
Classifier: Topic :: Internet :: WWW/HTTP
Classifier: Topic :: Internet :: WWW/HTTP :: Site Management
Classifier: Topic :: Text Processing
Classifier: Topic :: Text Processing :: Filters
Classifier: Topic :: Text Processing :: Markup
Classifier: Topic :: Text Processing :: Markup :: HTML
Classifier: Topic :: Utilities
